json_equationer/__init__.py
json_equationer/equation_creator.py
json_equationer/equation_evaluator.py
json_equationer-2.2.data/data/LICENSE
json_equationer-2.2.data/data/README.md
json_equationer-2.2.dist-info/LICENSE
json_equationer-2.2.dist-info/METADATA
json_equationer-2.2.dist-info/WHEEL
json_equationer-2.2.dist-info/top_level.txt
json_equationer-2.2.dist-info/RECORD
